chesspos/__init__.py
chesspos/evaluation/__init__.py
chesspos/evaluation/monitoring.py
chesspos/models/__init__.py
chesspos/models/chessposition_inspectable_autoencoder.py
chesspos/models/cnn_autoencoder.py
chesspos/models/cnn_resnet_autoencoder.py
chesspos/models/dense.py
chesspos/models/dense_autoencoder.py
chesspos/models/deprecated_models.py
chesspos/models/saveable_model.py
chesspos/models/trainable_model.py
chesspos/preprocessing/__init__.py
chesspos/preprocessing/board_converter.py
chesspos/preprocessing/pgn_extract.py
chesspos/preprocessing/sample_generator.py
chesspos/preprocessing/utils.py
chesspos/search/binary_index.py
chesspos/search/embedding_index.py
chesspos/test/integration_tests.ipynb
chesspos/test/test_binary_index.py
chesspos/test/test_convert.py
chesspos/test/test_sample_generator.py
chesspos/test/test_utils.py
chesspos/tools/__init__.py
chesspos/tools/position_extractor.py
chesspos/utils/__init__.py
chesspos/utils/decorators.py
chesspos/utils/utils.py
chess_embedding-0.1.4.dist-info/LICENSE
chess_embedding-0.1.4.dist-info/WHEEL
chess_embedding-0.1.4.dist-info/METADATA
chess_embedding-0.1.4.dist-info/RECORD
